Metadata-Version: 1.0
Name: Pyga-set
Version: 0.1
Summary: Pyga_set
Home-page: UNKNOWN
Author: UNKNOWN
Author-email: den.gavrin@mail.ru
License: UNKNOWN
Platform: UNKNOWN
